cartography/__init__.py
cartography/__main__.py
cartography/_version.py
cartography/cli.py
cartography/config.py
cartography/py.typed
cartography/stats.py
cartography/sync.py
cartography/util.py
cartography/client/__init__.py
cartography/client/aws/__init__.py
cartography/client/aws/ecr.py
cartography/client/aws/iam.py
cartography/client/core/__init__.py
cartography/client/core/tx.py
cartography/client/gcp/artifact_registry.py
cartography/client/gitlab/__init__.py
cartography/client/gitlab/container_images.py
cartography/data/__init__.py
cartography/data/azure_permission_relationships.yaml
cartography/data/gcp_permission_relationships.yaml
cartography/data/indexes.cypher
cartography/data/permission_relationships.yaml
cartography/data/jobs/__init__.py
cartography/data/jobs/analysis/__init__.py
cartography/data/jobs/analysis/aws_ec2_asset_exposure.json
cartography/data/jobs/analysis/aws_ec2_keypair_analysis.json
cartography/data/jobs/analysis/aws_ecs_asset_exposure.json
cartography/data/jobs/analysis/aws_eks_asset_exposure.json
cartography/data/jobs/analysis/aws_foreign_accounts.json
cartography/data/jobs/analysis/aws_lambda_ecr.json
cartography/data/jobs/analysis/gcp_compute_asset_inet_exposure.json
cartography/data/jobs/analysis/gcp_compute_instance_vpc_analysis.json
cartography/data/jobs/analysis/gcp_gke_asset_exposure.json
cartography/data/jobs/analysis/gcp_gke_basic_auth.json
cartography/data/jobs/analysis/gsuite_human_link.json
cartography/data/jobs/analysis/keycloak_inheritance.json
cartography/data/jobs/cleanup/__init__.py
cartography/data/jobs/cleanup/aws_account_cleanup.json
cartography/data/jobs/cleanup/aws_import_config_cleanup.json
cartography/data/jobs/cleanup/aws_import_ec2_launch_configurations_cleanup.json
cartography/data/jobs/cleanup/aws_import_ecr_cleanup.json
cartography/data/jobs/cleanup/aws_import_ecs_cleanup.json
cartography/data/jobs/cleanup/aws_import_elasticache_cleanup.json
cartography-0.127.0.dist-info/licenses/LICENSE
cartography-0.127.0.dist-info/METADATA
cartography-0.127.0.dist-info/WHEEL
cartography-0.127.0.dist-info/entry_points.txt
cartography-0.127.0.dist-info/top_level.txt
cartography-0.127.0.dist-info/RECORD
