Metadata-Version: 2.4
Name: cartography
Version: 0.127.0
Summary: Explore assets and their relationships across your technical infrastructure.
Maintainer: Cartography Contributors
License-Expression: Apache-2.0
Project-URL: Homepage, https://cartography-cncf.github.io/cartography
Project-URL: Documentation, https://cartography-cncf.github.io/cartography
Project-URL: Repository, https://github.com/cartography-cncf/cartography
Project-URL: Issues, https://github.com/cartography-cncf/cartography/issues
Project-URL: Changelog, https://github.com/cartography-cncf/cartography/releases
Classifier: Development Status :: 4 - Beta
Classifier: Intended Audience :: Developers
Classifier: Natural Language :: English
Classifier: Programming Language :: Python
Classifier: Programming Language :: Python :: 3
Classifier: Programming Language :: Python :: 3.10
Classifier: Topic :: Security
Classifier: Topic :: Software Development :: Libraries
Classifier: Topic :: Software Development :: Libraries :: Python Modules
Requires-Python: >=3.10
License-File: LICENSE
Requires-Dist: backoff>=2.1.2
Requires-Dist: boto3>=1.15.1
Requires-Dist: aioboto3>=13.0.0
Requires-Dist: httpx>=0.24.0
Requires-Dist: botocore>=1.18.1
Requires-Dist: dnspython>=1.15.0
Requires-Dist: neo4j<6.0.0,>=5.28.2
Requires-Dist: policyuniverse>=1.1.0.0
Requires-Dist: google-api-python-client>=1.7.8
Requires-Dist: google-auth>=2.37.0
Requires-Dist: marshmallow>=3.0.0rc7
Requires-Dist: oci>=2.71.0
Requires-Dist: okta<1.0.0
Requires-Dist: pyyaml>=5.3.1
Requires-Dist: requests>=2.22.0
Requires-Dist: statsd
Requires-Dist: packaging
Requires-Dist: python-digitalocean>=1.16.0
Requires-Dist: adal>=1.2.4
Requires-Dist: azure-cli-core>=2.26.0
Requires-Dist: azure-mgmt-compute>=5.0.0
Requires-Dist: azure-mgmt-containerinstance>=10.0.0
Requires-Dist: azure-mgmt-keyvault>=10.0.0
Requires-Dist: azure-mgmt-resource>=10.2.0
Requires-Dist: azure-mgmt-cosmosdb>=6.0.0
Requires-Dist: azure-mgmt-web>=7.0.0
Requires-Dist: azure-mgmt-eventgrid>=10.0.0
Requires-Dist: azure-mgmt-logic>=10.0.0
Requires-Dist: azure-mgmt-eventhub>=10.1.0
Requires-Dist: azure-keyvault-secrets>=4.0.0
Requires-Dist: azure-keyvault-keys>=4.0.0
Requires-Dist: azure-keyvault-certificates>=4.0.0
Requires-Dist: azure-mgmt-datafactory>=8.0.0
Requires-Dist: azure-mgmt-containerservice>=30.0.0
Requires-Dist: azure-mgmt-network>=25.0.0
Requires-Dist: azure-mgmt-security>=5.0.0
Requires-Dist: azure-mgmt-monitor>=3.0.0
Requires-Dist: msrestazure>=0.6.4
Requires-Dist: azure-mgmt-storage>=16.0.0
Requires-Dist: azure-mgmt-sql<=1.0.0
Requires-Dist: azure-mgmt-authorization>=0.60.0
Requires-Dist: azure-identity>=1.5.0
Requires-Dist: msgraph-sdk
Requires-Dist: kubernetes>=22.6.0
Requires-Dist: pdpyras>=4.3.0
Requires-Dist: crowdstrike-falconpy>=0.5.1
Requires-Dist: python-dateutil
Requires-Dist: xmltodict
Requires-Dist: duo-client
Requires-Dist: cloudflare<5.0.0,>=4.1.0
Requires-Dist: scaleway>=2.10.0
Requires-Dist: google-cloud-resource-manager>=1.14.2
Requires-Dist: google-cloud-asset>=1.0.0
Requires-Dist: types-aiobotocore-ecr
Requires-Dist: typer>=0.9.0
Requires-Dist: azure-mgmt-synapse>=2.0.0
Requires-Dist: azure-synapse-artifacts>=0.17.0
Requires-Dist: slack-sdk>=3.37.0
Dynamic: license-file
